py3o.template-0.10.0-nspkg.pth
py3o/template/__init__.py
py3o/template/data_struct.py
py3o/template/helpers.py
py3o/template/main.py
py3o/template/tests/test_helpers.py
py3o/template/tests/test_templates.py
py3o/template/tests/templates/image_injection_result.xml
py3o/template/tests/templates/keepboundary_detection_false.xml
py3o/template/tests/templates/keepboundary_detection_true.xml
py3o/template/tests/templates/list_content.xml
py3o/template/tests/templates/move_four.xml
py3o/template/tests/templates/move_four_result.xml
py3o/template/tests/templates/move_one.xml
py3o/template/tests/templates/move_one_result.xml
py3o/template/tests/templates/move_siblings.xml
py3o/template/tests/templates/move_siblings_result_1.xml
py3o/template/tests/templates/move_siblings_result_2.xml
py3o/template/tests/templates/move_three.xml
py3o/template/tests/templates/move_three_result.xml
py3o/template/tests/templates/move_two.xml
py3o/template/tests/templates/move_two_result.xml
py3o/template/tests/templates/ods_value_styles_result.xml
py3o/template/tests/templates/odt_value_styles_result.xml
py3o/template/tests/templates/py3o_access_global_variable.odt
py3o/template/tests/templates/py3o_access_global_variable_inside_loop.odt
py3o/template/tests/templates/py3o_access_in_loop_variable.odt
py3o/template/tests/templates/py3o_access_in_loop_variable_with_attribute.odt
py3o/template/tests/templates/py3o_access_in_loop_variable_with_multiple_attribute.odt
py3o/template/tests/templates/py3o_access_parent_variable_in_nested_loop.odt
py3o/template/tests/templates/py3o_access_parent_variable_in_nested_loop_with_attribute.odt
py3o/template/tests/templates/py3o_access_variable_in_nested_loop.odt
py3o/template/tests/templates/py3o_all_in_one_for_loop.odt
py3o/template/tests/templates/py3o_double_loop_on_same_object.odt
py3o/template/tests/templates/py3o_enumerate.odt
py3o/template/tests/templates/py3o_example_invalid_template.odt
py3o.template-0.10.0.dist-info/DESCRIPTION.rst
py3o.template-0.10.0.dist-info/METADATA
py3o.template-0.10.0.dist-info/RECORD
py3o.template-0.10.0.dist-info/WHEEL
py3o.template-0.10.0.dist-info/entry_points.txt
py3o.template-0.10.0.dist-info/metadata.json
py3o.template-0.10.0.dist-info/namespace_packages.txt
py3o.template-0.10.0.dist-info/top_level.txt
py3o.template-0.10.0.dist-info/zip-safe
