Metadata-Version: 1.1
Name: py3o.template
Version: 0.10.0
Summary: An easy solution to design reports using LibreOffice
Home-page: http://bitbucket.org/faide/py3o.template
Author: Florent Aide
Author-email: florent.aide@gmail.com
License: MIT License
Keywords: LibreOffice OpenOffice templating PDF
Platform: UNKNOWN
Classifier: Programming Language :: Python
Classifier: Topic :: Software Development :: Libraries :: Python Modules
Classifier: Development Status :: 4 - Beta
Classifier: Intended Audience :: Developers
Classifier: License :: OSI Approved :: MIT License
Classifier: Operating System :: OS Independent
